odoo/addons/purchase_analytic_global/README.rst
odoo/addons/purchase_analytic_global/__init__.py
odoo/addons/purchase_analytic_global/__manifest__.py
odoo/addons/purchase_analytic_global/i18n/es.po
odoo/addons/purchase_analytic_global/i18n/fr.po
odoo/addons/purchase_analytic_global/i18n/it.po
odoo/addons/purchase_analytic_global/i18n/purchase_analytic_global.pot
odoo/addons/purchase_analytic_global/models/__init__.py
odoo/addons/purchase_analytic_global/models/purchase.py
odoo/addons/purchase_analytic_global/readme/CONTRIBUTORS.rst
odoo/addons/purchase_analytic_global/readme/CREDITS.rst
odoo/addons/purchase_analytic_global/readme/DESCRIPTION.rst
odoo/addons/purchase_analytic_global/static/description/icon.png
odoo/addons/purchase_analytic_global/static/description/index.html
odoo/addons/purchase_analytic_global/tests/__init__.py
odoo/addons/purchase_analytic_global/tests/test_purchase_analytic_global.py
odoo/addons/purchase_analytic_global/views/purchase.xml
odoo14_addon_purchase_analytic_global-14.0.1.0.1.dev9.dist-info/METADATA
odoo14_addon_purchase_analytic_global-14.0.1.0.1.dev9.dist-info/WHEEL
odoo14_addon_purchase_analytic_global-14.0.1.0.1.dev9.dist-info/top_level.txt
odoo14_addon_purchase_analytic_global-14.0.1.0.1.dev9.dist-info/RECORD
